sdim/__init__.py
sdim/circuit.py
sdim/circuit_io.py
sdim/diophantine.py
sdim/gatedata.py
sdim/program.py
sdim/random_circuit.py
sdim/tableau/COMPOSITE.md
sdim/tableau/__init__.py
sdim/tableau/dataclasses.py
sdim/tableau/tableau_composite.py
sdim/tableau/tableau_gates.py
sdim/tableau/tableau_optimized.py
sdim/tableau/tableau_prime.py
sdim/unitary.py
sdim-1.3.3.dist-info/LICENSE
sdim-1.3.3.dist-info/METADATA
sdim-1.3.3.dist-info/WHEEL
sdim-1.3.3.dist-info/RECORD
