Metadata-Version: 2.3
Name: sdim
Version: 1.3.3
Summary: A tableau Clifford simulator for qudits
License: GPL-3.0-or-later
Keywords: quantum computing,Clifford simulator,qudits
Author: Steven Nguyen
Author-email: steven.n.nguyen@rutgers.edu
Requires-Python: >=3.11,<4.0
Classifier: License :: OSI Approved :: GNU General Public License v3 (GPLv3)
Classifier: License :: OSI Approved :: GNU General Public License v3 or later (GPLv3+)
Classifier: Operating System :: OS Independent
Classifier: Programming Language :: Python :: 3
Classifier: Programming Language :: Python :: 3.11
Classifier: Programming Language :: Python :: 3.12
Classifier: Programming Language :: Python :: 3.13
Requires-Dist: Diophantine
Requires-Dist: cirq (>=1.0.0)
Requires-Dist: networkx (>=3.4.2,<4.0.0)
Requires-Dist: numba
Requires-Dist: numpy (>=1.25.0)
Requires-Dist: sympy (>=1.12.1)
Project-URL: Documentation, https://events555.github.io/sdim/sdim.html
Project-URL: Homepage, https://events555.github.io/sdim/sdim.html
Project-URL: Repository, https://github.com/events555/sdim
